COPYING
README
pyano.cfg.example
setup.py
pyano/__init__.py
pyano/block.py
pyano/config.py
pyano/interface.py
pyano/mail.py
pyano/mix.py
pyano/news.py
pyano/security.py
pyano/stats.py
pyano/validate.py
pyano.egg-info/PKG-INFO
pyano.egg-info/SOURCES.txt
pyano.egg-info/dependency_links.txt
pyano.egg-info/top_level.txt
pyano.egg-info/zip-safe