Metadata-Version: 1.0
Name: pyano
Version: 0.6
Summary: Mixmaster web interface for mod_python
Home-page: http://pyanon.sourceforge.net
Author: Sean Whitbeck
Author-email: sean@neush.net
License: GPLv3
Keywords: mixmaster remailer web interface
Platform: UNKNOWN
